<screens mod="Week 02: Organization of the Body; Musculoskeletal System">
	
	<screen id="1" hasSub ="" isSub="" subOff="" nestedOff="" type="staticimage" screenName="screen_01a">
		<screenTitle><![CDATA[Introduction]]></screenTitle>
	</screen>
	<screen id="2" hasSub ="" isSub="" subOff="" nestedOff="" type="textwithimage" screenName="screen_01">
		<screenTitle><![CDATA[Organization of the Body; Musculoskeletal System]]></screenTitle>
	</screen>
	<screen id="3" hasSub ="" isSub="" subOff="" nestedOff="" type="topicvideo" screenName="screen_02">
		<screenTitle><![CDATA[Organization of the Body]]></screenTitle>
	</screen>
	<screen id="4" hasSub ="" isSub="" subOff="" nestedOff="" type="clickablethumbnail5" screenName="screen_03">
		<screenTitle><![CDATA[Body Systems]]></screenTitle>
	</screen>
	<screen id="5" hasSub ="" isSub="" subOff="" nestedOff="" type="draganddrop1" screenName="screen_04">
		<screenTitle><![CDATA[Check Your Knowledge]]></screenTitle>
	</screen>
	<screen id="6" hasSub ="" isSub="" subOff="" nestedOff="" type="topicvideo" screenName="screen_05">
		<screenTitle><![CDATA[Body Cavities and Organs]]></screenTitle>
	</screen>
	<screen id="7" hasSub ="" isSub="" subOff="" nestedOff="" type="Identification" screenName="screen_06">
		<screenTitle><![CDATA[Check Your Knowledge]]></screenTitle> 
	</screen>
	<screen id="8" hasSub ="" isSub="" subOff="" nestedOff="" type="clickReveal2" screenName="screen_07">
		<screenTitle><![CDATA[Planes of the Body]]></screenTitle>
	</screen>
	<screen id="9" hasSub ="" isSub="" subOff="" nestedOff="" type="draganddrop2_3tab" screenName="screen_08">
		<screenTitle><![CDATA[Check Your Knowledge]]></screenTitle> 
	</screen>
	<screen id="10" hasSub ="" isSub="" subOff="" nestedOff="" type="draganddrop1" screenName="screen_09">
		<screenTitle><![CDATA[Check Your Knowledge]]></screenTitle>
	</screen>
	<screen id="11" hasSub ="" isSub="" subOff="" nestedOff="" type="termAudio" screenName="screen_10">
		<screenTitle><![CDATA[Combining Forms]]></screenTitle>
	</screen>
	<screen id="12" hasSub ="" isSub="" subOff="" nestedOff="" type="termAudio" screenName="screen_11">
		<screenTitle><![CDATA[Combining Forms]]></screenTitle>
	</screen>
	<screen id="13" hasSub ="" isSub="" subOff="" nestedOff="" type="draganddrop1" screenName="screen_12">
		<screenTitle><![CDATA[Check Your Knowledge]]></screenTitle>
	</screen>
	<screen id="14" hasSub ="" isSub="" subOff="" nestedOff="" type="clickablethumbnail2" screenName="screen_13">
		<screenTitle><![CDATA[Musculoskeletal System]]></screenTitle>
	</screen>
	<screen id="15" hasSub ="" isSub="" subOff="" nestedOff="" type="topicvideo" screenName="screen_14">
		<screenTitle><![CDATA[Bones of the Upper Body]]></screenTitle>
	</screen>
	<screen id="16" hasSub ="" isSub="" subOff="" nestedOff="" type="topicvideo" screenName="screen_15">
		<screenTitle><![CDATA[Bones of the Lower Body]]></screenTitle>
	</screen>	
	<screen id="17" hasSub ="" isSub="" subOff="" nestedOff="" type="draganddrop2_6tab" screenName="screen_16">
		<screenTitle><![CDATA[Check Your Knowledge]]></screenTitle> 
	</screen>
	<screen id="18" hasSub ="" isSub="" subOff="" nestedOff="" type="draganddrop1" screenName="screen_17">
		<screenTitle><![CDATA[Check Your Knowledge]]></screenTitle>
	</screen>
	<screen id="19" hasSub ="" isSub="" subOff="" nestedOff="" type="topicvideo" screenName="screen_18">
		<screenTitle><![CDATA[Divisions of the Spinal Column]]></screenTitle>
	</screen>
	<screen id="20" hasSub ="" isSub="" subOff="" nestedOff="" type="draganddrop2" screenName="screen_19">
		<screenTitle><![CDATA[Check Your Knowledge]]></screenTitle> 
	</screen>
	<screen id="21" hasSub ="" isSub="" subOff="" nestedOff="" type="topicvideo" screenName="screen_20">
		<screenTitle><![CDATA[Muscles of the Upper Body]]></screenTitle>
	</screen>
	<screen id="22" hasSub ="" isSub="" subOff="" nestedOff="" type="termAudio" screenName="screen_21">
		<screenTitle><![CDATA[Combining Forms]]></screenTitle>
	</screen>
	<screen id="23" hasSub ="" isSub="" subOff="" nestedOff="" type="draganddrop1" screenName="screen_22">
		<screenTitle><![CDATA[Check Your Knowledge]]></screenTitle>
	</screen>
	<screen id="24" hasSub ="" isSub="" subOff="" nestedOff="" type="tabverticle" screenName="screen_23">
		<screenTitle><![CDATA[Ligaments and Tendons]]></screenTitle>
	</screen>
	<screen id="25" hasSub ="" isSub="" subOff="" nestedOff="" type="termAudio" screenName="screen_24">
		<screenTitle><![CDATA[Pathology of the Musculoskeletal System]]></screenTitle>
	</screen>
	<screen id="26" hasSub ="" isSub="" subOff="" nestedOff="" type="tabverticle" screenName="screen_25">
		<screenTitle><![CDATA[Treatments and Procedures]]></screenTitle>
	</screen>
	<screen id="27" hasSub ="" isSub="" subOff="" nestedOff="" type="tabhorizontal" screenName="screen_26">
		<screenTitle><![CDATA[Lab Tests and Diagnostics]]></screenTitle>
	</screen>
	<screen id="28" hasSub ="" isSub="" subOff="" nestedOff="" type="topicvideo" screenName="screen_27">
		<screenTitle><![CDATA[Useful Abbreviations]]></screenTitle>
	</screen>
	<screen id="29" hasSub ="" isSub="" subOff="" nestedOff="" type="mcq" screenName="screen_28">
		<screenTitle><![CDATA[Check Your Knowledge]]></screenTitle>
	</screen>
	<screen id="30" hasSub ="" isSub="" subOff="" nestedOff="" type="draganddrop1" screenName="screen_29">
		<screenTitle><![CDATA[Check Your Knowledge]]></screenTitle>
	</screen>	
	
</screens>